samba_sampler/__init__.py
samba_sampler/__main__.py
samba_sampler/common.py
samba_sampler/newick.py
samba_sampler/sampling.py
samba_sampler/etc/gled.matrix.bz2
samba_sampler/etc/global_tree.gled.newick
samba_sampler/etc/glottolog.v4.7-30-gafab84d5c4.tsv
samba_sampler/etc/haversine.matrix.bz2
samba_sampler/etc/walking.matrix.bz2
samba_sampler-0.3.2.dist-info/AUTHORS.md
samba_sampler-0.3.2.dist-info/LICENSE
samba_sampler-0.3.2.dist-info/METADATA
samba_sampler-0.3.2.dist-info/WHEEL
samba_sampler-0.3.2.dist-info/entry_points.txt
samba_sampler-0.3.2.dist-info/top_level.txt
samba_sampler-0.3.2.dist-info/RECORD
