Metadata-Version: 2.1
Name: samba-sampler
Version: 0.3.2
Summary: A Python package providing sampling methods via matrix-based distance measures to mitigate autocorrelation
Home-page: https://github.com/tresoldi/samba_sampler
Author: Tiago Tresoldi
Author-email: tiago@tresoldi.org
License: GPL-3.0
Project-URL: Documentation, https://samba_sampler.readthedocs.io
Keywords: sampling algorithm,language sampling,weighted sampling,phylogenetic autocorrelation,areal autocorrelation,linguistics,typology
Classifier: Operating System :: OS Independent
Classifier: Programming Language :: Python :: 3
Classifier: Topic :: Software Development :: Libraries
Classifier: Development Status :: 5 - Production/Stable
Classifier: Intended Audience :: Developers
Classifier: Intended Audience :: Education
Classifier: Intended Audience :: Science/Research
Classifier: Topic :: Text Processing :: Indexing
Classifier: Topic :: Text Processing :: Linguistic
Requires-Python: >=3.8
License-File: LICENSE
License-File: AUTHORS.md
Provides-Extra: dev
Requires-Dist: black ; extra == 'dev'
Requires-Dist: flake8 ; extra == 'dev'
Requires-Dist: twine ; extra == 'dev'
Requires-Dist: wheel ; extra == 'dev'
Provides-Extra: test
Requires-Dist: pytest ; extra == 'test'
